deepmol/__init__.py
deepmol/base/__init__.py
deepmol/base/_serializer.py
deepmol/base/estimator.py
deepmol/base/predictor.py
deepmol/base/transformer.py
deepmol/compound_featurization/__init__.py
deepmol/compound_featurization/_constants.py
deepmol/compound_featurization/_mhfp.py
deepmol/compound_featurization/_utils.py
deepmol/compound_featurization/base_featurizer.py
deepmol/compound_featurization/biosynfoni.py
deepmol/compound_featurization/deepchem_featurizers.py
deepmol/compound_featurization/mhfp.py
deepmol/compound_featurization/mixed_descriptors.py
deepmol/compound_featurization/mol2vec.py
deepmol/compound_featurization/nc_mfp_generator.py
deepmol/compound_featurization/neural_npfp_generator.py
deepmol/compound_featurization/np_classifier_fp.py
deepmol/compound_featurization/one_hot_encoder.py
deepmol/compound_featurization/rdkit_descriptors.py
deepmol/compound_featurization/rdkit_fingerprints.py
deepmol/compound_featurization/similarity_matrix.py
deepmol/compound_featurization/mol2vec_models/model_300dim.pkl
deepmol/compound_featurization/nc_mfp/Fingerprint_representation_step.py
deepmol/compound_featurization/nc_mfp/Fragment_identifying_step.py
deepmol/compound_featurization/nc_mfp/Fragment_list_generation_step.py
deepmol/compound_featurization/nc_mfp/Preprocessing_step.py
deepmol/compound_featurization/nc_mfp/SFCP_assigning_step.py
deepmol/compound_featurization/nc_mfp/Scaffold_matching_step.py
deepmol/compound_featurization/nc_mfp/__init__.py
deepmol/compound_featurization/nc_mfp/generate_database.py
deepmol/compound_featurization/nc_mfp/identify_smarts_fragmets.py
deepmol/compound_featurization/nc_mfp/databases/All_Optimized_Scaffold_List.txt
deepmol/compound_featurization/nc_mfp/databases/ncdb/final_label.pickle
deepmol/compound_featurization/nc_mfp/databases/ncdb/fragment_dic.pickle
deepmol/compound_featurization/neural_npfp/__init__.py
deepmol/compound_featurization/neural_npfp/ae_cv0.pt
deepmol/compound_featurization/neural_npfp/aux_cv0.pt
deepmol-1.1.18.dist-info/licenses/LICENSE
deepmol-1.1.18.dist-info/METADATA
deepmol-1.1.18.dist-info/WHEEL
deepmol-1.1.18.dist-info/dependency_links.txt
deepmol-1.1.18.dist-info/top_level.txt
deepmol-1.1.18.dist-info/RECORD
