Metadata-Version: 2.4
Name: deepmol
Version: 1.1.18
Summary: DeepMol: a python-based machine and deep learning framework for drug discovery
Author: DeepMol Team
License: BSD 2-Clause License
Keywords: machine-learning,deep-learning,cheminformatics,drug-discovery
Platform: unix
Platform: linux
Platform: osx
Platform: cygwin
Platform: win32
Classifier: Programming Language :: Python :: 3
Classifier: Programming Language :: Python :: 3 :: Only
Classifier: Programming Language :: Python :: 3.9
Classifier: Programming Language :: Python :: 3.10
Requires-Python: >=3.9
License-File: LICENSE
Requires-Dist: rdkit==2023.9.6
Requires-Dist: cached_property==1.5.2
Requires-Dist: seaborn
Requires-Dist: joblib
Requires-Dist: pillow
Requires-Dist: h5py
Requires-Dist: timeout_decorator==0.5.0
Provides-Extra: rdkit
Requires-Dist: rdkit==2023.9.6; extra == "rdkit"
Provides-Extra: test
Requires-Dist: h5py; extra == "test"
Requires-Dist: joblib; extra == "test"
Requires-Dist: tox>=3.25.0; extra == "test"
Requires-Dist: pillow; extra == "test"
Requires-Dist: numpy; extra == "test"
Requires-Dist: dill==0.3.6; extra == "test"
Requires-Dist: mypy>=0.942; extra == "test"
Requires-Dist: flake8>=4.0.1; extra == "test"
Requires-Dist: pytest>=7.1.1; extra == "test"
Requires-Dist: pandas<=2.0.0; extra == "test"
Requires-Dist: pytest-cov>=3.0.0; extra == "test"
Requires-Dist: smilespe==0.0.3; extra == "test"
Requires-Dist: seaborn; extra == "test"
Requires-Dist: cached_property==1.5.2; extra == "test"
Requires-Dist: rdkit==2023.9.6; extra == "test"
Provides-Extra: deep-learning
Requires-Dist: tensorflow==2.15.0; extra == "deep-learning"
Requires-Dist: tensorflow-probability==0.23.0; extra == "deep-learning"
Requires-Dist: IPython; extra == "deep-learning"
Requires-Dist: umap-learn==0.5.1; extra == "deep-learning"
Requires-Dist: kaleido==0.2.1; extra == "deep-learning"
Requires-Dist: pydantic; extra == "deep-learning"
Requires-Dist: timeout_decorator==0.5.0; extra == "deep-learning"
Requires-Dist: torch==2.5.1; extra == "deep-learning"
Requires-Dist: h5py; extra == "deep-learning"
Requires-Dist: deepchem==2.8.0; extra == "deep-learning"
Requires-Dist: joblib; extra == "deep-learning"
Requires-Dist: optuna==4.1.0; extra == "deep-learning"
Requires-Dist: biosynfoni; extra == "deep-learning"
Requires-Dist: numpy; extra == "deep-learning"
Requires-Dist: torch_geometric==2.6.1; extra == "deep-learning"
Requires-Dist: dgllife==0.3.2; extra == "deep-learning"
Requires-Dist: torchvision; extra == "deep-learning"
Requires-Dist: scikit-multilearn==0.2.0; extra == "deep-learning"
Requires-Dist: pillow; extra == "deep-learning"
Requires-Dist: plotly; extra == "deep-learning"
Requires-Dist: pandas<=2.0.0; extra == "deep-learning"
Requires-Dist: smilespe==0.0.3; extra == "deep-learning"
Requires-Dist: seaborn; extra == "deep-learning"
Requires-Dist: dgl<=2.0.0; extra == "deep-learning"
Requires-Dist: imblearn; extra == "deep-learning"
Requires-Dist: scikeras==0.12.0; extra == "deep-learning"
Requires-Dist: scikit-learn<1.6; extra == "deep-learning"
Requires-Dist: dill==0.3.6; extra == "deep-learning"
Requires-Dist: kneed==0.8.2; extra == "deep-learning"
Requires-Dist: chembl_structure_pipeline==1.1.0; extra == "deep-learning"
Requires-Dist: shap==0.44.0; extra == "deep-learning"
Requires-Dist: cached_property==1.5.2; extra == "deep-learning"
Requires-Dist: rdkit==2023.9.6; extra == "deep-learning"
Provides-Extra: machine-learning
Requires-Dist: IPython; extra == "machine-learning"
Requires-Dist: umap-learn==0.5.1; extra == "machine-learning"
Requires-Dist: kaleido==0.2.1; extra == "machine-learning"
Requires-Dist: timeout_decorator==0.5.0; extra == "machine-learning"
Requires-Dist: h5py; extra == "machine-learning"
Requires-Dist: joblib; extra == "machine-learning"
Requires-Dist: boruta==0.4.3; extra == "machine-learning"
Requires-Dist: optuna==4.1.0; extra == "machine-learning"
Requires-Dist: biosynfoni; extra == "machine-learning"
Requires-Dist: numpy; extra == "machine-learning"
Requires-Dist: scikit-multilearn==0.2.0; extra == "machine-learning"
Requires-Dist: pillow; extra == "machine-learning"
Requires-Dist: plotly; extra == "machine-learning"
Requires-Dist: pandas<=2.0.0; extra == "machine-learning"
Requires-Dist: smilespe==0.0.3; extra == "machine-learning"
Requires-Dist: seaborn; extra == "machine-learning"
Requires-Dist: imblearn; extra == "machine-learning"
Requires-Dist: scikit-learn<1.6; extra == "machine-learning"
Requires-Dist: dill==0.3.6; extra == "machine-learning"
Requires-Dist: kneed==0.8.2; extra == "machine-learning"
Requires-Dist: chembl_structure_pipeline==1.1.0; extra == "machine-learning"
Requires-Dist: shap==0.44.0; extra == "machine-learning"
Requires-Dist: cached_property==1.5.2; extra == "machine-learning"
Requires-Dist: rdkit==2023.9.6; extra == "machine-learning"
Provides-Extra: preprocessing
Requires-Dist: imblearn; extra == "preprocessing"
Requires-Dist: chembl_structure_pipeline==1.1.0; extra == "preprocessing"
Requires-Dist: h5py; extra == "preprocessing"
Requires-Dist: joblib; extra == "preprocessing"
Requires-Dist: pillow; extra == "preprocessing"
Requires-Dist: numpy; extra == "preprocessing"
Requires-Dist: dill==0.3.6; extra == "preprocessing"
Requires-Dist: timeout_decorator==0.5.0; extra == "preprocessing"
Requires-Dist: IPython; extra == "preprocessing"
Requires-Dist: pandas<=2.0.0; extra == "preprocessing"
Requires-Dist: boruta==0.4.3; extra == "preprocessing"
Requires-Dist: biosynfoni; extra == "preprocessing"
Requires-Dist: smilespe==0.0.3; extra == "preprocessing"
Requires-Dist: seaborn; extra == "preprocessing"
Requires-Dist: cached_property==1.5.2; extra == "preprocessing"
Requires-Dist: rdkit==2023.9.6; extra == "preprocessing"
Provides-Extra: smilespe
Requires-Dist: smilespe==0.0.3; extra == "smilespe"
Provides-Extra: seaborn
Requires-Dist: seaborn; extra == "seaborn"
Provides-Extra: joblib
Requires-Dist: joblib; extra == "joblib"
Provides-Extra: pillow
Requires-Dist: pillow; extra == "pillow"
Provides-Extra: h5py
Requires-Dist: h5py; extra == "h5py"
Provides-Extra: pandas
Requires-Dist: pandas<=2.0.0; extra == "pandas"
Provides-Extra: cached-property
Requires-Dist: cached_property==1.5.2; extra == "cached-property"
Provides-Extra: numpy
Requires-Dist: numpy; extra == "numpy"
Provides-Extra: dill
Requires-Dist: dill==0.3.6; extra == "dill"
Provides-Extra: shap
Requires-Dist: shap==0.44.0; extra == "shap"
Provides-Extra: ipython
Requires-Dist: IPython; extra == "ipython"
Provides-Extra: imblearn
Requires-Dist: imblearn; extra == "imblearn"
Provides-Extra: umap-learn
Requires-Dist: umap-learn==0.5.1; extra == "umap-learn"
Provides-Extra: kneed
Requires-Dist: kneed==0.8.2; extra == "kneed"
Provides-Extra: kaleido
Requires-Dist: kaleido==0.2.1; extra == "kaleido"
Provides-Extra: plotly
Requires-Dist: plotly; extra == "plotly"
Provides-Extra: chembl-structure-pipeline
Requires-Dist: chembl_structure_pipeline==1.1.0; extra == "chembl-structure-pipeline"
Provides-Extra: timeout-decorator
Requires-Dist: timeout_decorator==0.5.0; extra == "timeout-decorator"
Provides-Extra: biosynfoni
Requires-Dist: biosynfoni; extra == "biosynfoni"
Provides-Extra: torchvision
Requires-Dist: torchvision; extra == "torchvision"
Provides-Extra: torch
Requires-Dist: torch==2.5.1; extra == "torch"
Provides-Extra: dgl
Requires-Dist: dgl<=2.0.0; extra == "dgl"
Provides-Extra: scikeras
Requires-Dist: scikeras==0.12.0; extra == "scikeras"
Provides-Extra: dgllife
Requires-Dist: dgllife==0.3.2; extra == "dgllife"
Provides-Extra: deepchem
Requires-Dist: deepchem==2.8.0; extra == "deepchem"
Provides-Extra: torch-geometric
Requires-Dist: torch_geometric==2.6.1; extra == "torch-geometric"
Provides-Extra: tensorflow
Requires-Dist: tensorflow==2.15.0; extra == "tensorflow"
Provides-Extra: tensorflow-probability
Requires-Dist: tensorflow-probability==0.23.0; extra == "tensorflow-probability"
Provides-Extra: boruta
Requires-Dist: boruta==0.4.3; extra == "boruta"
Provides-Extra: scikit-learn
Requires-Dist: scikit-learn<1.6; extra == "scikit-learn"
Provides-Extra: optuna
Requires-Dist: optuna==4.1.0; extra == "optuna"
Provides-Extra: scikit-multilearn
Requires-Dist: scikit-multilearn==0.2.0; extra == "scikit-multilearn"
Provides-Extra: pydantic
Requires-Dist: pydantic; extra == "pydantic"
Provides-Extra: pytest
Requires-Dist: pytest>=7.1.1; extra == "pytest"
Provides-Extra: pytest-cov
Requires-Dist: pytest-cov>=3.0.0; extra == "pytest-cov"
Provides-Extra: mypy
Requires-Dist: mypy>=0.942; extra == "mypy"
Provides-Extra: flake8
Requires-Dist: flake8>=4.0.1; extra == "flake8"
Provides-Extra: tox
Requires-Dist: tox>=3.25.0; extra == "tox"
Provides-Extra: all
Requires-Dist: tensorflow==2.15.0; extra == "all"
Requires-Dist: tensorflow-probability==0.23.0; extra == "all"
Requires-Dist: flake8>=4.0.1; extra == "all"
Requires-Dist: IPython; extra == "all"
Requires-Dist: umap-learn==0.5.1; extra == "all"
Requires-Dist: kaleido==0.2.1; extra == "all"
Requires-Dist: pydantic; extra == "all"
Requires-Dist: timeout_decorator==0.5.0; extra == "all"
Requires-Dist: torch==2.5.1; extra == "all"
Requires-Dist: shap==0.44.0; extra == "all"
Requires-Dist: h5py; extra == "all"
Requires-Dist: deepchem==2.8.0; extra == "all"
Requires-Dist: joblib; extra == "all"
Requires-Dist: pytest-cov>=3.0.0; extra == "all"
Requires-Dist: optuna==4.1.0; extra == "all"
Requires-Dist: boruta==0.4.3; extra == "all"
Requires-Dist: biosynfoni; extra == "all"
Requires-Dist: numpy; extra == "all"
Requires-Dist: torch_geometric==2.6.1; extra == "all"
Requires-Dist: dgllife==0.3.2; extra == "all"
Requires-Dist: scikit-multilearn==0.2.0; extra == "all"
Requires-Dist: pillow; extra == "all"
Requires-Dist: plotly; extra == "all"
Requires-Dist: mypy>=0.942; extra == "all"
Requires-Dist: pandas<=2.0.0; extra == "all"
Requires-Dist: tox>=3.25.0; extra == "all"
Requires-Dist: seaborn; extra == "all"
Requires-Dist: smilespe==0.0.3; extra == "all"
Requires-Dist: dgl<=2.0.0; extra == "all"
Requires-Dist: imblearn; extra == "all"
Requires-Dist: scikeras==0.12.0; extra == "all"
Requires-Dist: scikit-learn<1.6; extra == "all"
Requires-Dist: dill==0.3.6; extra == "all"
Requires-Dist: pytest>=7.1.1; extra == "all"
Requires-Dist: kneed==0.8.2; extra == "all"
Requires-Dist: chembl_structure_pipeline==1.1.0; extra == "all"
Requires-Dist: torchvision; extra == "all"
Requires-Dist: cached_property==1.5.2; extra == "all"
Requires-Dist: rdkit==2023.9.6; extra == "all"
Dynamic: license-file
Dynamic: provides-extra
